{
  "questions": [
    {
      "id": 1,
      "value": "see it coming",
      "options": [
        "理解する",
        "予想する",
        "後悔する",
        "経験する"
      ],
      "correctAnswer": "予想する",
      "explanation": "「see it coming」は、何かが起こるのを事前に予測することを意味します。多くの場合、悪い事態や驚くべき事態について使われます。例：I should have seen it coming when she started avoiding my calls.（彼女が電話を避けるようになったとき、予感すべきだった。）"
    },
    {
      "id": 2,
      "value": "bitch about",
      "options": [
        "賞賛する",
        "文句を言う",
        "無視する",
        "改善する"
      ],
      "correctAnswer": "文句を言う",
      "explanation": "「bitch about」は、不満や文句を言うという意味の口語表現です。しばしば、些細なことや、どうしようもないことに対して使われます。ややネガティブなニュアンスがあります。例：He's always bitching about his job.（彼はいつも仕事について文句を言っている。）"
    },
    {
      "id": 3,
      "value": "hissy fit",
      "options": [
        "冗談",
        "激怒",
        "秘密",
        "策略"
      ],
      "correctAnswer": "激怒",
      "explanation": "「hissy fit」は、かんしゃく、取り乱すという意味で、特に子供や女性が感情的にヒステリックになる様子を指す軽蔑的な表現です。大げさな感情の爆発や不合理な怒りを伴うことが多いです。例：She threw a hissy fit when she didn't get what she wanted. (彼女は欲しいものが手に入らなかったとき、かんしゃくを起こした。)"
    },
    {
      "id": 4,
      "value": "put up with",
      "options": [
        "我慢する",
        "尊敬する",
        "反論する",
        "協力する"
      ],
      "correctAnswer": "我慢する",
      "explanation": "「put up with」は、嫌なことや不快な状況、人を我慢するという意味です。耐え忍ぶ、許容するといったニュアンスを含みます。例：I don't know how she puts up with him.（彼女がどうして彼を我慢できるのかわからない。）"
    },
    {
      "id": 5,
      "value": "nag",
      "options": [
        "褒める",
        "口うるさく言う",
        "助ける",
        "無視する"
      ],
      "correctAnswer": "口うるさく言う",
      "explanation": "「nag」は、しつこく文句を言う、小言を言うという意味です。特に、細かいことを繰り返し指摘して相手を困らせるような状況で使われます。例：She's always nagging me about cleaning my room.（彼女はいつも私の部屋を掃除するように小言を言う。）"
    },
    {
      "id": 6,
      "value": "bowel movements",
      "options": [
        "食事",
        "運動",
        "排便",
        "睡眠"
      ],
      "correctAnswer": "排便",
      "explanation": "「bowel movement」は排便を意味する医学用語ですが、日常会話でも使われます。Sheldonの発言は、Leonardが公共の場で不適切な話題を持ち出すことへの不満を示しています。"
    },
    {
      "id": 7,
      "value": "eulogy",
      "options": [
        "謝罪",
        "賛辞",
        "警告",
        "命令"
      ],
      "correctAnswer": "賛辞",
      "explanation": "「eulogy」は、故人を偲んで述べる追悼の辞、賛辞のことです。葬儀や追悼式で、故人の功績や人柄を称えるために行われます。Sheldonの発言は、場をわきまえない行動を批判しています。"
    },
    {
      "id": 8,
      "value": "touch the ground",
      "options": [
        "完成させる",
        "開始する",
        "地面につく",
        "改善する"
      ],
      "correctAnswer": "地面につく",
      "explanation": "この文脈では、ルームメイト契約書が地面に落ちることを指しています。Sheldonは契約書をアメリカ国旗に例え、それを地面に落とすことを冒涜的な行為だと主張しています。"
    },
    {
      "id": 9,
      "value": "crazy bastard",
      "options": [
        "親友",
        "素晴らしい人",
        "ばかげたやつ",
        "勇敢な人"
      ],
      "correctAnswer": "ばかげたやつ",
      "explanation": "「bastard」は、相手を侮辱する言葉で、軽蔑や怒りを表します。この文脈では、LeonardがSheldonに対して抱いている不満と怒りを強調しています。使用には注意が必要です。"
    },
    {
      "id": 10,
      "value": "big wigs",
      "options": [
        "重要な人物",
        "年配の従業員",
        "新しい同僚",
        "厳しい上司"
      ],
      "correctAnswer": "重要な人物",
      "explanation": "「big wig」は、組織や会社における重要な人物、重役を指す口語表現です。影響力のある地位にいる人を指します。例：The meeting was attended by all the big wigs in the company. (会議には会社の重役全員が出席した。)"
    },
    {
      "id": 11,
      "value": "side effect",
      "options": [
        "主な効果",
        "副作用",
        "隠された利益",
        "即効性"
      ],
      "correctAnswer": "副作用",
      "explanation": "「side effect」は、薬や治療の主な効果とは別に現れる、予期しない、または望ましくない効果を指します。医学的な文脈でよく使われます。例：One of the side effects of this medication is drowsiness. (この薬の副作用の一つは眠気です。)"
    },
    {
      "id": 12,
      "value": "anal leakage",
      "options": [
        "皮膚の炎症",
        "便秘",
        "肛門からの漏れ",
        "消化不良"
      ],
      "correctAnswer": "肛門からの漏れ",
      "explanation": "「anal leakage」は、肛門から便が漏れる症状を指します。医学的な話題であり、ここでは薬の副作用として言及されています。直接的な表現なので、会話の際には注意が必要です。"
    },
    {
      "id": 13,
      "value": "rebrand",
      "options": [
        "値下げする",
        "再編成する",
        "ブランドイメージを変える",
        "販売中止にする"
      ],
      "correctAnswer": "ブランドイメージを変える",
      "explanation": "「rebrand」は、製品や企業のブランドイメージを刷新し、新しいターゲット層にアピールしたり、古くなったイメージを払拭したりすることを意味します。マーケティング戦略の一つです。例：The company decided to rebrand itself to attract a younger audience. (会社は若い世代を引きつけるために、ブランドイメージを変えることにした。)"
    },
    {
      "id": 14,
      "value": "make lemonade",
      "options": [
        "パーティーを開く",
        "困難を乗り越える",
        "休憩する",
        "新しい友達を作る"
      ],
      "correctAnswer": "困難を乗り越える",
      "explanation": "「make lemonade (out of lemons)」は、困難な状況や不運を逆手にとって良い結果を生み出す、ピンチをチャンスに変えるという意味のイディオムです。例：When life gives you lemons, make lemonade. (人生が酸っぱいレモンを与えるなら、それを使って美味しいレモネードを作りなさい。)"
    },
    {
      "id": 15,
      "value": "emotional wreck",
      "options": [
        "冷静な人",
        "感情的に不安定な人",
        "楽観的な人",
        "知的な人"
      ],
      "correctAnswer": "感情的に不安定な人",
      "explanation": "「emotional wreck」は、感情的に非常に不安定で、精神的に打ちのめされている状態の人を指します。失恋や悲しい出来事の後に使われることが多いです。例：After the breakup, she was an emotional wreck. (別れのあと、彼女は感情的に打ちのめされていた。)"
    },
    {
      "id": 16,
      "value": "check in on",
      "options": [
        "無視する",
        "訪問して様子を見る",
        "招待する",
        "手伝う"
      ],
      "correctAnswer": "訪問して様子を見る",
      "explanation": "「check in on」は、誰かの状態や状況を確認するために、訪問したり連絡を取ったりすることを意味します。特に、相手が困難な状況にある場合や心配な場合に用いられます。例：I need to check in on my grandmother to make sure she's okay. (祖母の様子を見に行かなければならない。)"
    },
    {
      "id": 17,
      "value": "hit a few hot spots",
      "options": [
        "運動する",
        "有名な場所を巡る",
        "食事を作る",
        "勉強する"
      ],
      "correctAnswer": "有名な場所を巡る",
      "explanation": "「hit a few hot spots」は、人気の場所やナイトクラブなどをいくつか訪れるという意味の口語表現です。特に、娯楽や社交を楽しむ目的で使われます。例：We're going to hit a few hot spots in the city tonight. (今夜、市内のいくつかの人気スポットに行く予定だ。)"
    },
    {
      "id": 18,
      "value": "get lucky",
      "options": [
        "成功する",
        "幸運を手に入れる",
        "異性と親密になる",
        "宝くじに当たる"
      ],
      "correctAnswer": "異性と親密になる",
      "explanation": "「get lucky」は、性的な意味合いで、異性と親密な関係になる、または成功することを婉曲的に表現する口語表現です。やや軽薄なニュアンスがあります。例：He went to the bar hoping to get lucky. (彼は運が良ければいいなと思ってバーに行った。)"
    },
    {
      "id": 19,
      "value": "break down",
      "options": [
        "故障する",
        "感情的に崩れる",
        "詳細に分析する",
        "合意に達する"
      ],
      "correctAnswer": "感情的に崩れる",
      "explanation": "この文脈では、「break down」は精神的に参ってしまう、感情的に崩れるという意味で使用されています。Rajがクラブでうまくいかない状況を想像する中で、希望を失ってしまう様子を表しています。他の意味としては、機械が故障する、交渉が決裂する、などを意味します。"
    },
    {
      "id": 20,
      "value": "give up on",
      "options": [
        "熱中する",
        "あきらめる",
        "挑戦する",
        "依存する"
      ],
      "correctAnswer": "あきらめる",
      "explanation": "「give up on」は、人や物事に対して希望を捨て、あきらめるという意味です。多くの場合、努力が無駄に終わったと感じたときに使われます。例：I've given up on finding a good job in this town. (この町で良い仕事を見つけるのは諦めた。)"
    },
    {
      "id": 21,
      "value": "insufferable",
      "options": [
        "我慢できない",
        "素晴らしい",
        "友好的な",
        "正直な"
      ],
      "correctAnswer": "我慢できない",
      "explanation": "「insufferable」は、耐えられない、我慢できないという意味です。非常に不快で、容認できないほど嫌な人や状況を指します。例：He's an insufferable know-it-all. (彼は鼻持ちならない物知り屋だ。)"
    },
    {
      "id": 22,
      "value": "have had it",
      "options": [
        "楽しむ",
        "うんざりする",
        "達成する",
        "忘れる"
      ],
      "correctAnswer": "うんざりする",
      "explanation": "「have had it」は、もう我慢できない、うんざりだという意味の口語表現です。限界に達したときに使われます。例：I've had it with this job. I'm quitting. (この仕事にはもううんざりだ。辞める。)"
    },
    {
      "id": 23,
      "value": "done",
      "options": [
        "完了した",
        "疲れた",
        "興奮した",
        "準備ができた"
      ],
      "correctAnswer": "疲れた",
      "explanation": "ここでは「done」は「I am done」の省略形で、「もううんざりだ」「もうたくさんだ」という意味を表します。限界を感じて、何かを終わらせたい気持ちを示す時に使われます。"
    },
    {
      "id": 24,
      "value": "egotistical",
      "options": [
        "謙虚な",
        "利己的な",
        "思いやりのある",
        "勇敢な"
      ],
      "correctAnswer": "利己的な",
      "explanation": "「egotistical」は、自己中心的で、自分のことばかり考えているという意味です。自分の能力や重要性を過大評価し、他人に対する配慮に欠ける人を指します。類義語として「narcissistic」があります。例：He is egotistical and only cares about himself."
    },
    {
      "id": 25,
      "value": "make such a cute couple",
      "options": [
        "魅力的なカップルである",
        "不快なカップルである",
        "面白いカップルである",
        "悲しいカップルである"
      ],
      "correctAnswer": "魅力的なカップルである",
      "explanation": "「make such a cute couple」は、二人がとても可愛らしいカップルに見える、または相性が良さそうに見えるという意味です。恋愛関係にある二人を褒める際に使われます。"
    },
    {
      "id": 26,
      "value": "get by",
      "options": [
        "出発する",
        "生活する",
        "到着する",
        "成功する"
      ],
      "correctAnswer": "生活する",
      "explanation": "「get by」は、十分ではないかもしれないが、何とかやりくりして生活する、という意味です。特に経済的な困難な状況で使われます。例：It's difficult to get by on a small salary. (少ない給料で生活するのは難しい。)"
    },
    {
      "id": 27,
      "value": "whipping boy",
      "options": [
        "遊び相手",
        "いじめられっ子",
        "親友",
        "競争相手"
      ],
      "correctAnswer": "いじめられっ子",
      "explanation": "「whipping boy」は、他人の罪や失敗の責任を不当に負わされる人、または非難や罰を受ける人を指します。歴史的には、王族の子供の遊び相手で、子供が罰せられる代わりに罰を受けた子供を指しました。例：He's always been the whipping boy for the team's failures. (彼はいつもチームの失敗のいじめられっ子だった。)"
    },
    {
      "id": 28,
      "value": "stooge",
      "options": [
        "操り人形",
        "友人",
        "リーダー",
        "相談相手"
      ],
      "correctAnswer": "操り人形",
      "explanation": "「stooge」は、他人を笑わせるために、または他人の利益のために、利用される人、操り人形という意味です。コメディでよく使われる言葉で、おバカな役を演じる人を指すことがあります。例：He was used as a stooge in their scheme. (彼は彼らの計画の操り人形として利用された。)"
    },
    {
      "id": 29,
      "value": "doormat",
      "options": [
        "用心棒",
        "奴隷",
        "踏み台",
        "門番"
      ],
      "correctAnswer": "踏み台",
      "explanation": "「doormat」は、他人にいつも都合よく利用され、言いなりになっている人のことです。抵抗せず、自分の権利を主張しない人を軽蔑的に表現する言葉です。例：He's such a doormat; he lets everyone walk all over him. (彼は本当に踏み台だ。誰にでもいいようにされている。)"
    },
    {
      "id": 30,
      "value": "if it ain't broke",
      "options": [
        "壊れていないなら",
        "もしそれが盗まれたなら",
        "もしそれが高価なら",
        "もしそれが新しいなら"
      ],
      "correctAnswer": "壊れていないなら",
      "explanation": "「If it ain't broke, don't fix it.」ということわざの省略形で、「壊れていないなら、直すな」という意味です。問題がないものをわざわざいじって悪化させる必要はない、という考えを表します。現状維持を支持する際に用いられます。例：The system is working fine; if it ain't broke, don't fix it. (システムは正常に動作している。壊れていないなら、直すな。)"
    },
    {
      "id": 31,
      "value": "freak out",
      "options": [
        "冷静になる",
        "取り乱す",
        "楽しむ",
        "落ち着く"
      ],
      "correctAnswer": "取り乱す",
      "explanation": "「freak out」は、パニックになる、取り乱す、ひどく興奮する、という意味です。不安や恐怖、または強い感情によって冷静さを失う状態を表します。例：Don't freak out when you see the bill. (請求書を見ても取り乱さないで。)"
    },
    {
      "id": 32,
      "value": "tall glass of brown water",
      "options": [
        "美味しい飲み物",
        "魅力的な人",
        "背の高い人",
        "退屈な人"
      ],
      "correctAnswer": "退屈な人",
      "explanation": "「tall glass of brown water」は、魅力がない、つまらない、退屈な人を指す、少し変わった比喩表現です。魅力的な「一杯の水」に例えて、それが茶色であることで、その魅力のなさを強調しています。ユーモラスな文脈で使われることがあります。"
    },
    {
      "id": 33,
      "value": "doggie bag",
      "options": [
        "犬用の袋",
        "残り物を入れる袋",
        "特別な贈り物",
        "旅行用バッグ"
      ],
      "correctAnswer": "残り物を入れる袋",
      "explanation": "「doggie bag」は、レストランなどで食べきれなかった料理を持ち帰るための袋のことです。もともとは犬に与えるための残り物を入れる袋という意味でしたが、現在では人間が食べるために持ち帰る際にも使われます。例：Can I get a doggie bag for this? (これの残りをもらえますか？)"
    },
    {
      "id": 34,
      "value": "mind me",
      "options": [
        "私を気にする",
        "気にしないで",
        "私を尊敬する",
        "私を助ける"
      ],
      "correctAnswer": "気にしないで",
      "explanation": "「Don't mind me」は、「私のことは気にしないでください」という意味です。自分の行動や感情が他人に迷惑をかけるかもしれないときに、それを軽く受け流してほしいというニュアンスで使われます。例：Don't mind me, I'm just thinking aloud. (私のことは気にしないで、ただ独り言を言っているだけです。)"
    },
    {
      "id": 35,
      "value": "vintage",
      "options": [
        "最新の",
        "年代物の",
        "一般的な",
        "珍しい"
      ],
      "correctAnswer": "年代物の",
      "explanation": "「vintage」は、特定時代に製造された、価値のある、または高品質なものを指します。特に古いもの、年代物のものに使われ、古くて価値があるというニュアンスを含みます。例：a vintage car (年代物の車)"
    },
    {
      "id": 36,
      "value": "ethical conundrum",
      "options": [
        "倫理的な問題",
        "経済的な問題",
        "社会的な問題",
        "個人的な問題"
      ],
      "correctAnswer": "倫理的な問題",
      "explanation": "「ethical conundrum」は、倫理的な難題、倫理的なジレンマという意味です。道徳的な原則の間で選択を迫られ、どちらを選んでも問題があるような状況を指します。例：The company faced an ethical conundrum when deciding whether to lay off employees. (会社は従業員を解雇するかどうかを決定する際に、倫理的な難題に直面した。)"
    },
    {
      "id": 37,
      "value": "cultivate",
      "options": [
        "破壊する",
        "育てる",
        "無視する",
        "避ける"
      ],
      "correctAnswer": "育てる",
      "explanation": "「cultivate」は、才能や人間関係などを時間をかけて育む、という意味です。農業用語から派生し、精神的な成長や発展を促す文脈で使われます。例：She cultivated a strong network of contacts in the industry. (彼女は業界で強力な人脈を築いた。)"
    },
    {
      "id": 38,
      "value": "take in",
      "options": [
        "騙す",
        "理解する",
        "受け入れる",
        "拒否する"
      ],
      "correctAnswer": "受け入れる",
      "explanation": "「take in」は、ここでは「(人を) 受け入れる、住まわせる」という意味で使用されています。また、騙す、理解する、などの意味もあります。文脈によって意味が異なります。例：He was taken in by their lies. (彼は彼らの嘘に騙された。)"
    },
    {
      "id": 39,
      "value": "the mood struck him",
      "options": [
        "気分が乗った",
        "雨が降った",
        "雷が落ちた",
        "鐘が鳴った"
      ],
      "correctAnswer": "気分が乗った",
      "explanation": "「the mood struck him」は、「彼がふとその気になった」という意味です。何かをしたいという衝動や気分が急に起こったことを表します。例：He would just go whenever the mood struck him.(彼はただ、その気になったらいつでも行った。)"
    },
    {
      "id": 40,
      "value": "sign on",
      "options": [
        "署名する",
        "同意する",
        "拒否する",
        "確認する"
      ],
      "correctAnswer": "同意する",
      "explanation": "「sign on」は、契約に署名する、同意する、参加するという意味です。ここでは、「ルームメイトになることに同意する」という意味で使われています。例：I would sign on, no further questions asked. (私は同意するでしょう、それ以上の質問はなしで。)"
    },
    {
      "id": 41,
      "value": "chauffeur",
      "options": [
        "運転手",
        "医者",
        "弁護士",
        "先生"
      ],
      "correctAnswer": "運転手",
      "explanation": "「chauffeur」は、（特に金持ちなどの）お抱え運転手、という意味です。ここでは、AmyがSheldonの運転手をかってでるという意味で使われています。例：I'm willing to chauffeur you around town (私はあなたを町中に運転して連れて行くことを厭わない)"
    },
    {
      "id": 42,
      "value": "abhorrent",
      "options": [
        "魅力的な",
        "嫌悪感を抱かせる",
        "面白い",
        "興味深い"
      ],
      "correctAnswer": "嫌悪感を抱かせる",
      "explanation": "「abhorrent」は、非常に嫌な、嫌悪感を抱かせる、という意味です。道徳的に受け入れられないほど不快なものを指します。例：Racism is abhorrent to me. (人種差別は私にとって非常に嫌悪感を抱かせるものだ。)"
    },
    {
      "id": 43,
      "value": "rage-inducing",
      "options": [
        "幸福感",
        "怒りを誘発する",
        "喜び",
        "悲しみ"
      ],
      "correctAnswer": "怒りを誘発する",
      "explanation": "「rage-inducing」は、激しい怒りを引き起こす、という意味です。非常にイライラさせる、または不快な状況や行動を指します。例：His constant complaining is rage-inducing. (彼の絶え間ない不満は怒りを誘発する。)"
    },
    {
      "id": 44,
      "value": "cute as a button",
      "options": [
        "とても醜い",
        "とても可愛い",
        "とても退屈",
        "とても怖い"
      ],
      "correctAnswer": "とても可愛い",
      "explanation": "「cute as a button」は、非常に可愛い、愛らしい、という意味の慣用句です。小さなボタンのように小さくて可愛いものを連想させます。例：Sheldon's personality quirks, which others find abhorrent or rage-inducing, I find cute as a button. (シェルドンの性格の癖は、他の人が嫌悪感を抱いたり、怒りを誘発したりするかもしれませんが、私はとても可愛いと思っています。)"
    },
    {
      "id": 45,
      "value": "good buddy",
      "options": [
        "親友",
        "ただの知り合い",
        "敵",
        "上司"
      ],
      "correctAnswer": "親友",
      "explanation": "「good buddy」は、「良い相棒、親友」という意味です。親しみを込めて友人を呼ぶ際に使われます。ここでは、SheldonがLeonardとの関係を修復しようとして、わざとらしく使っています。"
    },
    {
      "id": 46,
      "value": "dust-up",
      "options": [
        "大掃除",
        "小競り合い",
        "パーティー",
        "お祝い"
      ],
      "correctAnswer": "小競り合い",
      "explanation": "「dust-up」は、口論、小競り合い、ちょっとした騒動という意味です。深刻な争いではなく、一時的な意見の衝突などを指します。例：They had a little dust-up over the parking space. (彼らは駐車スペースを巡ってちょっとした小競り合いをした。)"
    },
    {
      "id": 47,
      "value": "much ado about nothing",
      "options": [
        "無駄な努力",
        "取るに足らないこと",
        "素晴らしい成果",
        "悲しい出来事"
      ],
      "correctAnswer": "取るに足らないこと",
      "explanation": "「much ado about nothing」は、大騒ぎするほどのことでない、取るに足らないこと、という意味です。シェイクスピアの喜劇のタイトルとしても有名で、些細なことで騒ぎ立てる様子を指します。例：The argument was much ado about nothing. (その議論は大騒ぎするほどのことでなかった。)"
    },
    {
      "id": 48,
      "value": "spoiler alert",
      "options": [
        "ネタバレ注意",
        "危険",
        "お買い得情報",
        "交通情報"
      ],
      "correctAnswer": "ネタバレ注意",
      "explanation": "「spoiler alert」は、映画やドラマ、本などの内容について、これから見る人や読む人に事前に内容を知らせてしまう可能性がある場合に、注意を促すために使われる表現です。「ネタバレ注意」という意味です。"
    },
    {
      "id": 49,
      "value": "financially, it makes great sense",
      "options": [
        "経済的に意味がある",
        "感情的に意味がある",
        "論理的に意味がある",
        "道徳的に意味がある"
      ],
      "correctAnswer": "経済的に意味がある",
      "explanation": "「financially, it makes great sense」は、経済的に考えると非常に理にかなっている、という意味です。金銭的な面で大きな利点があることを示します。例：Living together, financially, it makes great sense. (一緒に住むことは、経済的に考えると非常に理にかなっている。)"
    },
    {
      "id": 50,
      "value": "to carry my stomach out of here like I'm a fireman rescuing an infant",
      "options": [
        "赤ちゃんを救出する消防士",
        "重すぎて運べない",
        "喜びで心が躍る",
        "空腹で元気がない"
      ],
      "correctAnswer": "重すぎて運べない",
      "explanation": "「to carry my stomach out of here like I'm a fireman rescuing an infant」は、ここでは比喩表現として使われており、「食べすぎてお腹がはちきれそうで、まるで消防士が赤ちゃんを救出するように（慎重に、または大変な思いで）お腹を運び出さなければならない」という意味です。過食による苦しさをユーモラスに表現しています。"
    },
    {
      "id": 51,
      "value": "devil-may-care",
      "options": [
        "無頓着な",
        "注意深い",
        "心配性の",
        "責任感の強い"
      ],
      "correctAnswer": "無頓着な",
      "explanation": "「devil-may-care」は、危険や結果を気にせず、無鉄砲で大胆な態度を表します。楽天的で、リスクを恐れない様子を示す際に用いられます。\n\n例：He had a devil-may-care attitude towards his finances. (彼はお金に関して無頓着だった。)"
    },
    {
      "id": 52,
      "value": "cut to the chase",
      "options": [
        "遠回しに話す",
        "本題に入る",
        "詳しく説明する",
        "議論する"
      ],
      "correctAnswer": "本題に入る",
      "explanation": "「cut to the chase」は、回りくどい話をやめて、最も重要な点や核心にすぐに触れることを意味します。時間や労力を節約したい場合に使う表現です。\n\n例：Let's cut to the chase - we need to decide on a budget. (本題に入ろう - 予算を決めなければなりません。)"
    },
    {
      "id": 53,
      "value": "lovable scamp",
      "options": [
        "愛すべき悪党",
        "嫌われ者",
        "ずる賢い人",
        "怠け者"
      ],
      "correctAnswer": "愛すべき悪党",
      "explanation": "「scamp」は、いたずら好きで、少しばかりの問題を起こすような人を指す言葉です。「lovable」と組み合わさることで、その人のいたずらっぽさが愛嬌として受け入れられているニュアンスを表します。\n\n例：He's a lovable scamp, always getting into trouble but always forgiven. (彼は愛すべき悪党で、いつもトラブルに巻き込まれるけど、いつも許される。)"
    },
    {
      "id": 54,
      "value": "marks a level of intimacy",
      "options": [
        "親密さのレベルを示す",
        "秘密を暴露する",
        "プライバシーを侵害する",
        "誤解を招く"
      ],
      "correctAnswer": "親密さのレベルを示す",
      "explanation": "「mark」は、何かの段階や程度を示すという意味で使われます。「a level of intimacy」と組み合わさることで、関係性の親密さの度合いが新たな段階に達することを意味します。\n\n例: Holding hands marks a level of intimacy in their relationship. (手をつなぐことは、彼らの関係において親密さのレベルを示す。)"
    },
    {
      "id": 55,
      "value": "laid out",
      "options": [
        "並べた",
        "隠した",
        "無視した",
        "急いだ"
      ],
      "correctAnswer": "並べた",
      "explanation": "「lay out」は、詳細に説明する、提示するという意味です。特に計画やアイデアを明確に示す際に使われます。\n\n例：She laid out her plans for the project in detail. (彼女はプロジェクトの計画を詳細に説明した。)"
    },
    {
      "id": 56,
      "value": "refute",
      "options": [
        "反論する",
        "同意する",
        "無視する",
        "受け入れる"
      ],
      "correctAnswer": "反論する",
      "explanation": "「refute」は、議論や主張に対して、証拠や論理を用いて誤りを指摘し、反論することを意味します。フォーマルな文脈で使われることが多いです。\n\n例：He refuted the allegations made against him. (彼は彼に対する申し立てに反論した。)"
    },
    {
      "id": 57,
      "value": "spoiler alert",
      "options": [
        "ネタバレ注意",
        "緊急警報",
        "秘密厳守",
        "情報公開"
      ],
      "correctAnswer": "ネタバレ注意",
      "explanation": "「spoiler alert」は、映画やドラマ、書籍などの内容について、事前に情報を知ってしまうと楽しみが損なわれる可能性がある場合に、警告として使われる表現です。\n\n例：Spoiler alert: The main character dies at the end. (ネタバレ注意：主人公は最後に死にます。)"
    },
    {
      "id": 58,
      "value": "rerun",
      "options": [
        "再放送",
        "新作",
        "生放送",
        "特別番組"
      ],
      "correctAnswer": "再放送",
      "explanation": "「rerun」は、テレビ番組などが再放送されることを意味します。\n\n例：We watched a rerun of our favorite show last night. (昨夜、私たちのお気に入りの番組の再放送を見ました。)"
    },
    {
      "id": 59,
      "value": "the next thing I know",
      "options": [
        "次に知ったことには",
        "何も知らない",
        "すべて理解している",
        "特に何も起こらなかった"
      ],
      "correctAnswer": "次に知ったことには",
      "explanation": "「the next thing I know」は、ある出来事の直後に、予期せぬ事態が起こったことを表す際に使われる表現です。何が起こったのかよく覚えていない、または事態が急展開したというニュアンスを含みます。\n\n例：I started reading the book, and the next thing I knew, it was morning. (本を読み始めたら、次に気づいたときには朝だった。)"
    },
    {
      "id": 60,
      "value": "tucking me into bed",
      "options": [
        "寝かしつける",
        "起こす",
        "ベッドから引きずり出す",
        "ベッドを整理する"
      ],
      "correctAnswer": "寝かしつける",
      "explanation": "「tuck someone into bed」は、誰かをベッドに寝かしつけ、毛布やシーツをかけてあげることを意味します。子供に対して行うことが多い行為ですが、ここではユーモラスに用いられています。\n\n例：My mom used to tuck me into bed every night when I was a child. (子供の頃、母は毎晩私を寝かしつけてくれた。)"
    },
    {
      "id": 61,
      "value": "Oy vey",
      "options": [
        "ああ、もう",
        "こんにちは",
        "ありがとう",
        "さようなら"
      ],
      "correctAnswer": "ああ、もう",
      "explanation": "「Oy vey」は、イディッシュ語由来の表現で、不満、驚き、落胆などを表す際に用いられます。英語圏では、特にユダヤ系の人がよく使う表現です。\n\n例：Oy vey, I forgot my keys again! (ああ、もう、また鍵を忘れた！)"
    },
    {
      "id": 62,
      "value": "cream sherry hangover",
      "options": [
        "甘いシェリー酒の二日酔い",
        "ワインの飲みすぎ",
        "ノンアルコールの飲み物",
        "健康的な食事"
      ],
      "correctAnswer": "甘いシェリー酒の二日酔い",
      "explanation": "「cream sherry」は甘口のシェリー酒の一種です。「hangover」は二日酔いを意味します。この二つが組み合わさることで、甘いシェリー酒を飲みすぎたことによる二日酔いを表します。\n\n例：He had a terrible cream sherry hangover after the party. (彼はパーティーの後、ひどい甘口シェリー酒の二日酔いだった。)"
    },
    {
      "id": 63,
      "value": "smell blintzes",
      "options": [
        "ブリンツの匂いがする",
        "香水をつける",
        "掃除をする",
        "料理をする"
      ],
      "correctAnswer": "ブリンツの匂いがする",
      "explanation": "「blintz」は、東欧系の料理で、クレープのような生地でチーズなどを包んだものです。ここでは、朝食にブリンツが用意されていることを匂いで感じていることを表しています。\n\n例: She smelled blintzes and knew her grandmother was visiting. (彼女はブリンツの匂いを嗅いで、祖母が来ていることを知った。)"
    },
    {
      "id": 64,
      "value": "home wrecker",
      "options": [
        "家庭崩壊させる人",
        "家の修理をする人",
        "引っ越し業者",
        "不動産業者"
      ],
      "correctAnswer": "家庭崩壊させる人",
      "explanation": "「home wrecker」は、他人の家庭や関係を破壊する人を指す言葉です。多くの場合、不倫関係にある人を指して使われます。\n\n例：She was labeled a home wrecker after having an affair with a married man. (彼女は既婚男性との不倫関係の後、家庭崩壊させる人というレッテルを貼られた。)"
    },
    {
      "id": 65,
      "value": "leg stubble",
      "options": [
        "足の剃り跡",
        "美しい脚",
        "足の怪我",
        "むくんだ足"
      ],
      "correctAnswer": "足の剃り跡",
      "explanation": "「stubble」は、剃った後に生えてきた短い毛のことを指します。「leg stubble」は、足の毛を剃った後に生えてきた短い毛を表します。ここでは、女性が足の毛を剃った後の状態を指しています。\n\n例：She forgot to shave her legs and had noticeable leg stubble. (彼女は脚を剃るのを忘れて、目立つ剃り跡があった。)"
    },
    {
      "id": 66,
      "value": "get some Drano",
      "options": [
        "排水口クリーナーを使う",
        "医者に診てもらう",
        "運動をする",
        "新しい服を買う"
      ],
      "correctAnswer": "排水口クリーナーを使う",
      "explanation": "「Drano」は、排水口の詰まりを解消するための洗剤のブランド名です。ここでは、比喩的に、問題のあるものを取り除く、解決するという意味で使われています。\n\n例：The pipes were clogged, so we had to get some Drano. (排水管が詰まっていたので、排水口クリーナーを使う必要があった。)"
    },
    {
      "id": 67,
      "value": "face the crying",
      "options": [
        "泣き顔に向き合う",
        "笑顔で挨拶する",
        "無視する",
        "喜びを分かち合う"
      ],
      "correctAnswer": "泣き顔に向き合う",
      "explanation": "「face」は、困難や問題に直面するという意味です。「crying」と組み合わさることで、泣いている人や悲しんでいる人に立ち向かう、またはそのような状況を受け入れることを意味します。\n\n例：I had to face the crying children after I told them the bad news. (悪い知らせを伝えた後、私は泣いている子供たちに向き合わなければならなかった。)"
    },
    {
      "id": 68,
      "value": "high-pitched wails of despair",
      "options": [
        "絶望的な悲鳴",
        "静かな悲しみ",
        "喜びの歌",
        "無関心な態度"
      ],
      "correctAnswer": "絶望的な悲鳴",
      "explanation": "「high-pitched」は、音が高いことを意味します。「wail」は、悲しみや苦痛を伴う泣き叫び声のことです。「despair」は絶望を表します。これらが組み合わさることで、非常に悲痛で絶望的な叫びを意味します。\n\n例：The high-pitched wails of despair filled the room after the tragic news was announced. (悲劇的なニュースが発表された後、絶望的な悲鳴が部屋に響き渡った。)"
    },
    {
      "id": 69,
      "value": "What were we thinking?",
      "options": [
        "私たちは何を考えていたんだろう？",
        "何を考えているの？",
        "何も考えていない",
        "良い考えがある"
      ],
      "correctAnswer": "私たちは何を考えていたんだろう？",
      "explanation": "「What were we thinking?」は、過去の行動を後悔したり、その愚かさを自問自答したりする際に使われる表現です。\n\n例：What were we thinking? We should have stayed home. (私たちは何を考えていたんだろう？ 家にいるべきだった。)"
    },
    {
      "id": 70,
      "value": "bend that far",
      "options": [
        "そこまで体を曲げる",
        "正直に話す",
        "妥協する",
        "嘘をつく"
      ],
      "correctAnswer": "そこまで体を曲げる",
      "explanation": "物理的に体を曲げる能力を指しますが、ここでは比喩的に、無理なことや困難なことを成し遂げるという意味合いで使われています。\n\n例：I can't bend that far to help him; it's too much for me to handle. (彼を助けるためにそこまで無理はできない。私には荷が重すぎる。)"
    },
    {
      "id": 71,
      "value": "do us both a favor",
      "options": [
        "私たち両方のためになる",
        "私だけのためになる",
        "誰のためにもならない",
        "彼らの邪魔をする"
      ],
      "correctAnswer": "私たち両方のためになる",
      "explanation": "「do someone a favor」は、誰かのために親切な行為をすることを意味します。「do us both a favor」は、私たち両方にとって利益になる、または都合が良いという意味合いで使われます。\n\n例：Could you do us both a favor and keep this a secret? (私たち両方のために、これを秘密にしておいてくれませんか？)"
    },
    {
      "id": 72,
      "value": "It's like",
      "options": [
        "まるで～のようだ",
        "それは違う",
        "本当のことだ",
        "どうでもいい"
      ],
      "correctAnswer": "まるで～のようだ",
      "explanation": "「It's like」は、何かを説明する際に、類似の状況や例えを用いて説明する際に使われる表現です。比較や比喩を用いて理解を深める効果があります。\n\n例：It's like trying to herd cats. (まるで猫を追いかけるようだ。)"
    },
    {
      "id": 73,
      "value": "a matter of time",
      "options": [
        "時間の問題",
        "緊急事態",
        "過去の問題",
        "解決済みの問題"
      ],
      "correctAnswer": "時間の問題",
      "explanation": "「a matter of time」は、何かが起こるのが時間の問題であることを意味します。必然的に起こることであり、時期がいつかという点に焦点が当てられています。\n\n例：It's just a matter of time before they announce their engagement. (彼らが婚約を発表するのは時間の問題だ。)"
    },
    {
      "id": 74,
      "value": "get this",
      "options": [
        "これを聞いて",
        "忘れて",
        "気にしないで",
        "関係ない"
      ],
      "correctAnswer": "これを聞いて",
      "explanation": "「get this」は、驚くべきことや興味深いことを伝える前に、相手の注意を引くために使われる表現です。「ちょっと聞いてよ」というニュアンスに近いです。\n\n例：Get this - I won the lottery! (ちょっと聞いてよ - 宝くじに当たったんだ！)"
    },
    {
      "id": 75,
      "value": "too late, pal",
      "options": [
        "もう遅いよ、相棒",
        "早く来て、友達",
        "いつでも歓迎だよ",
        "また今度ね"
      ],
      "correctAnswer": "もう遅いよ、相棒",
      "explanation": "「pal」は、親しい友人や仲間を指す言葉です。「too late, pal」は、機会を逃した、または状況が変わってしまったため、もう手遅れであることを伝える際に使われる表現です。\n\n例：You should have called earlier; it's too late, pal. (もっと早く電話すべきだったね。もう遅いよ、相棒。)"
    },
    {
      "id": 76,
      "value": "trapped",
      "options": [
        "解放された",
        "閉じ込められた",
        "助けられた",
        "楽しんでいる"
      ],
      "correctAnswer": "閉じ込められた",
      "explanation": "「trapped」は、文字通りには「罠にかけられた」という意味ですが、比喩的には「逃げられない状況にいる」「身動きが取れない」という意味で使われます。ここでは、ハワードの母親の家に閉じ込められてしまったラージの状況を表しています。"
    },
    {
      "id": 77,
      "value": "ran you a bath",
      "options": [
        "お風呂を走った",
        "お風呂を沸かした",
        "お風呂を壊した",
        "お風呂を売った"
      ],
      "correctAnswer": "お風呂を沸かした",
      "explanation": "「run a bath」は、お風呂にお湯を張る、お風呂を沸かすという意味の一般的な表現です。誰かのために風呂を沸かす場合は、「run someone a bath」となります。"
    },
    {
      "id": 78,
      "value": "rescue",
      "options": [
        "訪問",
        "救出",
        "非難",
        "無視"
      ],
      "correctAnswer": "救出",
      "explanation": "「rescue」は、危険な状態から誰かを救い出す、救助するという意味です。ここでは、ハワードの母親の家からラージを救い出すことを指しています。"
    },
    {
      "id": 79,
      "value": "Bar Mitzvah",
      "options": [
        "誕生日パーティー",
        "卒業式",
        "成人式",
        "結婚式"
      ],
      "correctAnswer": "成人式",
      "explanation": "「Bar Mitzvah」は、ユダヤ教の男子が13歳になった時に行う成人式のことです。ここでは、ラージがハワードの母親の家からなかなか抜け出せない状況を大げさに表現するために使われています。"
    },
    {
      "id": 80,
      "value": "the way Leonard used to",
      "options": [
        "レオナルドがよく使っていた道",
        "レオナルドが以前やっていたように",
        "レオナルドが望んでいた方法",
        "レオナルドの指示通りに"
      ],
      "correctAnswer": "レオナルドが以前やっていたように",
      "explanation": "「the way someone used to」は、「〜が以前やっていたように」「〜が昔やっていた方法で」という意味です。ここでは、エイミーがレオナルドの好みに合わせて中華料理を注文したことを示しています。"
    },
    {
      "id": 81,
      "value": "take the mystery out of",
      "options": [
        "謎を解き明かす",
        "魅力をなくす",
        "秘密にする",
        "興味を持つ"
      ],
      "correctAnswer": "魅力をなくす",
      "explanation": "「take the mystery out of」は、何かから神秘性や魅力を奪う、興味をそそらなくするという意味です。ここでは、同棲することで関係性がマンネリ化することを心配しているシェルドンに対して、エイミーが同棲しても関係は変わらないだろうと答えています。"
    },
    {
      "id": 82,
      "value": "take the liberty of",
      "options": [
        "自由を奪う",
        "勝手にする",
        "許可を取る",
        "注意を払う"
      ],
      "correctAnswer": "勝手にする",
      "explanation": "「take the liberty of」は、「〜する許可を得ずに（しかし失礼ではないと判断して）〜する」「〜することを勝手にする」という意味の丁寧な表現です。ここでは、エイミーがシェルドンと自分の留守番電話のメッセージを勝手に録音したことを伝えています。"
    },
    {
      "id": 83,
      "value": "outgoing voice mail message",
      "options": [
        "帰りの伝言",
        "発信メッセージ",
        "受信メッセージ",
        "秘密のメッセージ"
      ],
      "correctAnswer": "発信メッセージ",
      "explanation": "「outgoing voice mail message」は、留守番電話の応答メッセージ、発信メッセージのことです。電話をかけた人が最初に聞くメッセージを指します。"
    },
    {
      "id": 84,
      "value": "urban slang",
      "options": [
        "田舎の方言",
        "都会のスラング",
        "標準語",
        "法律用語"
      ],
      "correctAnswer": "都会のスラング",
      "explanation": "「urban slang」は、都市部でよく使われる俗語やスラングのことです。エイミーは、留守中に泥棒が入らないように、あえて乱暴な言葉遣いをしようとしています。"
    },
    {
      "id": 85,
      "value": "dopey",
      "options": [
        "賢い",
        "ばかげた",
        "面白い",
        "感動的な"
      ],
      "correctAnswer": "ばかげた",
      "explanation": "「dopey」は、「まぬけな」「ばかげた」「ぼんやりした」という意味です。ここでは、エイミーがシェルドンの好きな宇宙映画を少し馬鹿にするようなニュアンスで使っています。"
    },
    {
      "id": 86,
      "value": "ridiculous contract",
      "options": [
        "秘密の契約",
        "ばかげた契約",
        "有利な契約",
        "口頭契約"
      ],
      "correctAnswer": "ばかげた契約",
      "explanation": "「ridiculous contract」は、「ばかげた契約」「馬鹿らしい契約」という意味です。シェルドンがエイミーに提示した、交際に関する細かいルールを定めた契約のことを指しています。"
    },
    {
      "id": 87,
      "value": "snake in our garden",
      "options": [
        "庭のヘビ",
        "楽園の蛇",
        "庭の手入れ",
        "ペットの蛇"
      ],
      "correctAnswer": "楽園の蛇",
      "explanation": "「snake in the garden (of Eden)」は、「楽園の蛇」という聖書の引用から来ており、幸福な状況を破壊する人やものを指す比喩表現です。ここでは、ペニーがシェルドンとエイミーの同棲を妨げていると考えられています。"
    },
    {
      "id": 88,
      "value": "all set to",
      "options": [
        "全て準備された",
        "出発の準備ができた",
        "片付ける",
        "全て忘れた"
      ],
      "correctAnswer": "出発の準備ができた",
      "explanation": "「all set to」は、「～する準備ができている」「～する用意ができている」という意味です。ここでは、エイミーがシェルドンとの同棲に向けて準備万端だったことを強調しています。"
    },
    {
      "id": 89,
      "value": "get all huffy",
      "options": [
        "怒る",
        "喜ぶ",
        "悲しむ",
        "感謝する"
      ],
      "correctAnswer": "怒る",
      "explanation": "「get huffy」は、「むくれる」「ふくれる」「怒る」という意味です。不機嫌になったり、怒ったりする様子を表します。"
    },
    {
      "id": 90,
      "value": "catch up on",
      "options": [
        "最新情報を見る",
        "追いつく",
        "忘れる",
        "無視する"
      ],
      "correctAnswer": "最新情報を見る",
      "explanation": "「catch up on」は、「(しばらくぶりに)～の近況を知る」「(遅れを)取り戻す」という意味です。ここでは、シェルドンがウォーキング・デッドの最新エピソードを見ようと提案しています。"
    },
    {
      "id": 91,
      "value": "help me out",
      "options": [
        "私を助けて",
        "私を困らせて",
        "私を無視して",
        "私を笑わせて"
      ],
      "correctAnswer": "私を助けて",
      "explanation": "「help someone out」は、「（人が困難な状況から抜け出すのを）手伝う、助ける」という意味です。ラージがハワードに、母親の家から脱出するのを手伝ってほしいと頼んでいます。"
    },
    {
      "id": 92,
      "value": "the hell",
      "options": [
        "地獄",
        "一体全体",
        "天国",
        "運命"
      ],
      "correctAnswer": "一体全体",
      "explanation": "「what the hell」のように使われ、「一体全体」「何が」といった意味合いで、怒りや不満、驚きなどを表す際に用いられます。ここでは、シェルドンの態度に対するエイミーの怒りを表しています。"
    },
    {
      "id": 93,
      "value": "blaming it on me",
      "options": [
        "私を褒める",
        "私のせいにする",
        "私を許す",
        "私を無視する"
      ],
      "correctAnswer": "私のせいにする",
      "explanation": "「blame (something) on (someone)」は、「（何か）を（誰か）のせいにする」という意味です。ここでは、シェルドンがエイミーと同棲できない理由をペニーのせいにしていることを指しています。"
    },
    {
      "id": 94,
      "value": "the truth",
      "options": [
        "嘘",
        "真実",
        "秘密",
        "噂"
      ],
      "correctAnswer": "真実",
      "explanation": "「the truth」は、「真実、事実」という意味です。ペニーが、シェルドンが真実を愛するなら、エイミーに直接同棲したくない理由を言うべきだと主張しています。"
    },
    {
      "id": 95,
      "value": "the evidence does support that",
      "options": [
        "証拠はそれを否定する",
        "証拠はそれを支持する",
        "証拠は関係ない",
        "証拠は隠されている"
      ],
      "correctAnswer": "証拠はそれを支持する",
      "explanation": "「the evidence does support that」は、「証拠はそれを裏付けている」という意味です。シェルドンが自分が臆病者であることを認めつつ、それを客観的に述べている様子を表しています。"
    },
    {
      "id": 96,
      "value": "jerk",
      "options": [
        "親切な人",
        "嫌なやつ",
        "勇敢な人",
        "賢い人"
      ],
      "correctAnswer": "嫌なやつ",
      "explanation": "「jerk」は、「嫌なやつ」「ろくでなし」「ばか」といった意味で使われる軽蔑的な言葉です。ここでは、ペニーとエイミーがそれぞれの彼氏（レナードとシェルドン）を指して使っています。"
    },
    {
      "id": 97,
      "value": "the one where Lori dies",
      "options": [
        "ロリが生き残る話",
        "ロリが死ぬ話",
        "ロリが旅立つ話",
        "ロリが生まれる話"
      ],
      "correctAnswer": "ロリが死ぬ話",
      "explanation": "「the one where...」は、特定の状況や出来事が起こるエピソードを指す時に使われる表現です。ここでは、シェルドンがウォーキング・デッドの中でロリが死ぬエピソードについて話そうとしています。"
    },
    {
      "id": 98,
      "value": "climbing out of the window",
      "options": [
        "窓から入る",
        "窓から登る",
        "窓から降りる",
        "窓から逃げる"
      ],
      "correctAnswer": "窓から降りる",
      "explanation": "「climb out of the window」は、「窓からよじ登って出る」という意味です。ラージがハワードの母親の家からこっそり抜け出そうとしている状況を表しています。"
    },
    {
      "id": 99,
      "value": "What's up?",
      "options": [
        "どうしたの？",
        "どこに行くの？",
        "何が起きたの？",
        "元気ですか？"
      ],
      "correctAnswer": "どうしたの？",
      "explanation": "「What’s up?」は、人に会ったときの挨拶や、相手の状況を尋ねる際に使われる一般的な表現です。「元気ですか？」「何かあったの？」といった意味合いで使われます。"
    },
    {
      "id": 100,
      "value": "out dropping science",
      "options": [
        "科学を落とす",
        "科学的研究に出かける",
        "科学を教える",
        "科学を忘れる"
      ],
      "correctAnswer": "科学的研究に出かける",
      "explanation": "「dropping science」は、主にアフリカ系アメリカ人のコミュニティで使われるスラングで、「知識を広める」「教育的な話をする」「科学的な研究をする」といった意味合いがあります。ここでは、シェルドンとエイミーが科学的な活動に出かけることをユーモラスに表現しています。"
    }
  ]
}